cdk_pyproject/__init__.py
cdk_pyproject/py.typed
cdk_pyproject/py_project.py
cdk_pyproject/py_script.py
cdk_pyproject/utils.py
cdk_pyproject/dockerfiles/pyproject.Dockerfile
cdk_pyproject/dockerfiles/rye.Dockerfile
cdk_pyproject/dockerfiles/script.Dockerfile
cdk_pyproject/dockerfiles/uv.Dockerfile
cdk_pyproject-0.9.1.dist-info/METADATA
cdk_pyproject-0.9.1.dist-info/WHEEL
cdk_pyproject-0.9.1.dist-info/licenses/LICENSE
cdk_pyproject-0.9.1.dist-info/RECORD
