Metadata-Version: 2.4
Name: cdk-pyproject
Version: 0.9.1
Summary: Add your description here
Project-URL: Source, https://github.com/bayashi-cl/cdk-pyproject/
Author-email: Masaki Kobayashi <bayashi.cl@gmail.com>
License-File: LICENSE
Classifier: Development Status :: 4 - Beta
Classifier: Framework :: AWS CDK
Classifier: Framework :: AWS CDK :: 2
Classifier: License :: OSI Approved :: MIT License
Classifier: Programming Language :: Python :: 3 :: Only
Classifier: Programming Language :: Python :: 3.11
Classifier: Programming Language :: Python :: 3.12
Requires-Python: >=3.11
Requires-Dist: aws-cdk-lib>=2.138.0
Requires-Dist: pyproject-metadata>=0.8.0
